ultimarc/__init__.py
ultimarc/exceptions.py
ultimarc/main.py
ultimarc/misc.py
ultimarc/system_utils.py
ultimarc/test_usb.py
ultimarc/devices/__init__.py
ultimarc/devices/_base.py
ultimarc/devices/_device.py
ultimarc/devices/_mappings.py
ultimarc/devices/_structures.py
ultimarc/devices/aimtrak.py
ultimarc/devices/ipac2.py
ultimarc/devices/ipac4.py
ultimarc/devices/jpac.py
ultimarc/devices/mini_pac.py
ultimarc/devices/ultimate_io.py
ultimarc/devices/ultrastik.py
ultimarc/devices/usb_button.py
ultimarc/examples/README.md
ultimarc/examples/aimtrak.json
ultimarc/examples/ipac2.json
ultimarc/examples/ipac4.json
ultimarc/examples/jpac.json
ultimarc/examples/mini-pac.json
ultimarc/examples/ultrastik-analog.json
ultimarc/examples/ultrastik-controller-id.json
ultimarc/examples/ultrastik-djoy4way.json
ultimarc/examples/ultrastik-easyjoy8way.json
ultimarc/examples/ultrastik-joy2way.json
ultimarc/examples/ultrastik-joy4way.json
ultimarc/examples/ultrastik-joy8way.json
ultimarc/examples/ultrastik-map2way.json
ultimarc/examples/ultrastik-mouse.json
ultimarc/examples/ultrastik-pre-2015-map2way.json
ultimarc/examples/ultrastik-udbjoy4way.json
ultimarc/examples/ultrastik-vjoy2way.json
ultimarc/examples/usb-button-color.json
ultimarc/examples/usb-button-config.json
ultimarc/examples/ultimateIO/ultimate-io-led.json
ultimarc/examples/ultimateIO/ultimate-io-pin.json
ultimarc/locale/ultimarc.pot
ultimarc/qml/assets.qrc
ultimarc/qml/main.qml
ultimarc/qml/qml.qrc
ultimarc/qml/qmldir
ultimarc/qml/rc_assets.py
ultimarc/qml/windowsicon.qrc
ultimarc/qml/__pycache__/rc_assets.cpython-313.pyc
ultimarc/qml/assets/arcadeGameMachine.jpg
ultimarc/qml/assets/ultimarctitle.jpg
ultimarc/qml/complex/AboutDialog.qml
ultimarc/qml/complex/BackgroundImage.qml
ultimarc/qml/complex/ImageBar.qml
ultimarc/qml/complex/MacroPopup.qml
ultimarc/qml/complex/RGBSlider.qml
ultimarc/qml/dialogs/FileDialog.qml
ultimarc/qml/views/DeviceDetails.qml
ultimarc/qml/views/DeviceList.qml
ultimarc/qml/views/DeviceStackView.qml
ultimarc-1.0.0a9.dist-info/licenses/LICENSE
ultimarc-1.0.0a9.dist-info/METADATA
ultimarc-1.0.0a9.dist-info/WHEEL
ultimarc-1.0.0a9.dist-info/entry_points.txt
ultimarc-1.0.0a9.dist-info/top_level.txt
ultimarc-1.0.0a9.dist-info/RECORD
