Metadata-Version: 2.4
Name: Ultimarc
Version: 1.0.0a9
Summary: Tools for configuring Ultimarc USB devices
Home-page: https://github.com/katie-snow/QtPyUltimarc
Author: Katie Snow
Author-email: snowywhitewater@gmail.com
License: GNU General Public License v3 (GPLv3)
Project-URL: Homepage, https://github.com/katie-snow/QtPyUltimarc
Classifier: Development Status :: 3 - Alpha
Classifier: Intended Audience :: Developers
Classifier: License :: OSI Approved :: GNU General Public License v3 (GPLv3)
Classifier: Operating System :: MacOS :: MacOS X
Classifier: Operating System :: Microsoft :: Windows
Classifier: Operating System :: POSIX :: Linux
Classifier: Environment :: Console
Classifier: Environment :: X11 Applications :: Qt
Classifier: Programming Language :: Python :: 3
Classifier: Programming Language :: Python :: 3.9
Classifier: Programming Language :: Python :: 3.10
Classifier: Programming Language :: Python :: 3.11
Classifier: Programming Language :: Python :: 3.12
Classifier: Programming Language :: Python :: 3.13
Classifier: Topic :: Games/Entertainment :: Arcade
Classifier: Topic :: System :: Hardware :: Universal Serial Bus (USB)
Requires-Python: >=3.8
License-File: LICENSE
Requires-Dist: babel>=2.12.1
Requires-Dist: libusb>=1.0.26b5
Requires-Dist: fastjsonschema>=2.21.1
Requires-Dist: python-easy-json>=1.1.2
Provides-Extra: ui
Requires-Dist: pyside6>=6.5.0; extra == "ui"
Dynamic: license-file
